livesplit_parser/__init__.py
livesplit_parser/livesplit_parser.py
livesplit_parser-0.3.dist-info/LICENSE
livesplit_parser-0.3.dist-info/METADATA
livesplit_parser-0.3.dist-info/WHEEL
livesplit_parser-0.3.dist-info/top_level.txt
livesplit_parser-0.3.dist-info/RECORD
