Metadata-Version: 2.1
Name: livesplit_parser
Version: 0.3
Summary: Parse LiveSplit data
Author: Trevor Bushnell
Author-email: <tbushnell11@gmail.com>
Keywords: python,speedrunning,livesplit
License-File: LICENSE
Requires-Dist: pandas
Requires-Dist: numpy
Requires-Dist: xmltodict
Requires-Dist: matplotlib
Requires-Dist: seaborn
Requires-Dist: datetime
Requires-Dist: xlsxwriter
